deepcom.py
deepcom-0.1.0.dist-info/METADATA
deepcom-0.1.0.dist-info/WHEEL
deepcom-0.1.0.dist-info/licenses/LICENSE
deepcom-0.1.0.dist-info/RECORD
