Metadata-Version: 2.1
Name: deepcom
Version: 0.1.0
Summary: Research tools for communication-efficient deep learning
Project-URL: Homepage, https://github.com/mh-lan/deepcom
Project-URL: Bug Tracker, https://github.com/mh-lan/deepcom/issues
Author-email: Muhang Lan <mhlan@mail.ustc.edu.cn>
License-File: LICENSE
Classifier: License :: OSI Approved :: MIT License
Classifier: Operating System :: OS Independent
Classifier: Programming Language :: Python :: 3
Requires-Python: >=3.7
